UniversalSpeech/__init__.py
UniversalSpeech/exceptions.py
UniversalSpeech/load.py
UniversalSpeech/lib/SAAPI32.dll
UniversalSpeech/lib/UniversalSpeech.dll
UniversalSpeech/lib/UniversalSpeech.tlb
UniversalSpeech/lib/ZDSRAPI.dll
UniversalSpeech/lib/dolapi.dll
UniversalSpeech/lib/jfwapi.dll
UniversalSpeech/lib/nvdaControllerClient.dll
UniversalSpeech/lib64/SAAPI32.dll
UniversalSpeech/lib64/UniversalSpeech.dll
UniversalSpeech/lib64/UniversalSpeech.tlb
UniversalSpeech/lib64/ZDSRAPI.dll
UniversalSpeech/lib64/dolapi.dll
UniversalSpeech/lib64/jfwapi.dll
UniversalSpeech/lib64/nvdaControllerClient.dll
UniversalSpeech-1.0.2.1.dist-info/METADATA
UniversalSpeech-1.0.2.1.dist-info/WHEEL
UniversalSpeech-1.0.2.1.dist-info/top_level.txt
UniversalSpeech-1.0.2.1.dist-info/RECORD
