Metadata-Version: 2.1
Name: UniversalSpeech
Version: 1.0.2.1
Summary: UniversalSpeech simplifies speech access in applications through a unified interface, supporting diverse methods such as screen readers, direct synthesis, and native/OS speech engines.
Home-page: https://github.com/MahmoudAtef999/PythonUniversalSpeech/
Author: Mahmoud Atef
Author-email: mahmoud.atef.987123@gmail.com
Keywords: speech,accessibility,screen readerjaws,nvda
Classifier: Development Status :: 5 - Production/Stable
Classifier: Intended Audience :: Developers
Classifier: Operating System :: Microsoft :: Windows
Classifier: Programming Language :: Python :: 3
